codegen/__init__.py
codegen/codegen.py
codegen/codegen_fromDB.py
codegen/codegen_python.py
codegen/free_connex_codegen.py
codegen/database/__init__.py
codegen/database/baseDB.py
codegen/database/dbplan.py
codegen/database/postgresDB.py
codegen/node/__init__.py
codegen/node/cpp_nodes/BaseNode.py
codegen/node/cpp_nodes/FreeConnexJoinNode.py
codegen/node/cpp_nodes/FromNode.py
codegen/node/cpp_nodes/GroupbyNode.py
codegen/node/cpp_nodes/JoinNode.py
codegen/node/cpp_nodes/OrderByNode.py
codegen/node/cpp_nodes/SelectNode.py
codegen/node/cpp_nodes/WhereNode.py
codegen/node/cpp_nodes/__init__.py
codegen/node/python_nodes/SelectNode.py
codegen/node/python_nodes/WhereNode.py
codegen/node/python_nodes/__init__.py
codegen/node/templates/__init__.py
codegen/table/__init__.py
codegen/table/column.py
codegen/table/free_connex_table.py
codegen/table/python_free_connex_table.py
codegen/table/table.py
codegen/templates/__init__.py
codegen/tests/__init__.py
codegen/tests/data.py
codegen/tests/test_table_config.py
codegen/tests/basic_tests/__init__.py
codegen/tests/basic_tests/base_test_case.py
codegen/tests/basic_tests/test_column.py
codegen/tests/basic_tests/test_data_fetcher.py
codegen/tests/basic_tests/test_join.py
codegen/tests/basic_tests/test_load_json.py
codegen/tests/basic_tests/test_schema.py
codegen/tests/basic_tests/test_table.py
codegen/tests/cpp_tests/__init__.py
codegen/tests/cpp_tests/test_codegendb.py
codegen/tests/cpp_tests/test_join_node.py
codegen/tests/cpp_tests/test_parse_q13.py
codegen/tests/cpp_tests/test_parse_q3.py
codegen/tests/cpp_tests/test_query_plan_join.py
codegen/tests/cpp_tests/test_select.py
codegen/tests/python_tests/__init__.py
codegen/tests/python_tests/base_test.py
codegen/tests/python_tests/test_codegen_python.py
codegen/tests/python_tests/test_select_python.py
codegen/tests/test_data/__init__.py
codegen/utils/DataFetcher.py
codegen/utils/SchemaFetcher.py
codegen/utils/__init__.py
codegen/utils/createDBHelper.py
secyan_gen-0.0.1.dist-info/METADATA
secyan_gen-0.0.1.dist-info/WHEEL
secyan_gen-0.0.1.dist-info/top_level.txt
secyan_gen-0.0.1.dist-info/RECORD
