Metadata-Version: 2.1
Name: secyan-gen
Version: 0.0.1
Summary: Code parser with secyan_python
Home-page: UNKNOWN
Author: Qiwei Li
Author-email: sirily1997@gmail.com
License: UNKNOWN
Platform: any
Classifier: Programming Language :: Python :: 3.6
Classifier: Programming Language :: Python :: 3.7
Classifier: Programming Language :: Python :: 3.8
Classifier: Programming Language :: Python :: 3.9
Requires-Python: >=3.6
Requires-Dist: setuptools
Requires-Dist: wheel
